ten_utils/__init__.py
ten_utils/buffer.py
ten_utils/common/__init__.py
ten_utils/common/constants.py
ten_utils/common/decorators.py
ten_utils/common/singleton.py
ten_utils/common/errors/__init__.py
ten_utils/common/errors/base.py
ten_utils/common/errors/env_loader.py
ten_utils/common/validators/__init__.py
ten_utils/common/validators/env_loader.py
ten_utils/common/validators/logger.py
ten_utils/env_loader/__init__.py
ten_utils/env_loader/loader.py
ten_utils/log/__init__.py
ten_utils/log/config.py
ten_utils/log/logger.py
ten_utils-0.0.15.dist-info/licenses/LICENSE
ten_utils-0.0.15.dist-info/METADATA
ten_utils-0.0.15.dist-info/WHEEL
ten_utils-0.0.15.dist-info/top_level.txt
ten_utils-0.0.15.dist-info/RECORD
