Metadata-Version: 2.4
Name: ten_utils
Version: 0.0.15
Summary: A python library that implements many small tools that are often used in python development.
Author-email: Караваев Александр <234iskateli234@gmail.com>
License-Expression: MIT
Project-URL: Homepage, https://github.com/Ten-o69/ten-utils
Project-URL: BugTracker, https://github.com/Ten-o69/ten-utils/issues
Classifier: Programming Language :: Python :: 3
Classifier: Programming Language :: Python :: 3.12
Classifier: Operating System :: OS Independent
Classifier: Development Status :: 3 - Alpha
Classifier: Intended Audience :: Developers
Classifier: Topic :: Software Development :: Libraries
License-File: LICENSE
Requires-Dist: rich==13.9.4
Requires-Dist: python-dotenv==1.1.0
Requires-Dist: pydantic==2.11.3
Provides-Extra: dev
Requires-Dist: pytest; extra == "dev"
Dynamic: license-file
